{
  "type": "GROUP",
"name": "Global Information",
"path": "",
"pathFormatted": "group_missing-name-b06d1",
"stats": {
    "name": "Global Information",
    "numberOfRequests": {
        "total": 33966,
        "ok": 33958,
        "ko": 8
    },
    "minResponseTime": {
        "total": 12,
        "ok": 12,
        "ko": 359
    },
    "maxResponseTime": {
        "total": 20048,
        "ok": 19554,
        "ko": 20048
    },
    "meanResponseTime": {
        "total": 512,
        "ok": 510,
        "ko": 8307
    },
    "standardDeviation": {
        "total": 1364,
        "ok": 1352,
        "ko": 9131
    },
    "percentiles1": {
        "total": 214,
        "ok": 214,
        "ko": 2587
    },
    "percentiles2": {
        "total": 456,
        "ok": 456,
        "ko": 20017
    },
    "percentiles3": {
        "total": 2377,
        "ok": 2370,
        "ko": 20045
    },
    "percentiles4": {
        "total": 7161,
        "ok": 7129,
        "ko": 20047
    },
    "group1": {
    "name": "t < 800 ms",
    "count": 31199,
    "percentage": 92
},
    "group2": {
    "name": "800 ms < t < 1200 ms",
    "count": 511,
    "percentage": 2
},
    "group3": {
    "name": "t > 1200 ms",
    "count": 2248,
    "percentage": 7
},
    "group4": {
    "name": "failed",
    "count": 8,
    "percentage": 0
},
    "meanNumberOfRequestsPerSecond": {
        "total": 14.1525,
        "ok": 14.149166666666666,
        "ko": 0.0033333333333333335
    }
},
"contents": {
"req_01-01-admin-por-1106b": {
        "type": "REQUEST",
        "name": "01.01.Admin.Portal.Home",
"path": "01.01.Admin.Portal.Home",
"pathFormatted": "req_01-01-admin-por-1106b",
"stats": {
    "name": "01.01.Admin.Portal.Home",
    "numberOfRequests": {
        "total": 722,
        "ok": 722,
        "ko": 0
    },
    "minResponseTime": {
        "total": 12,
        "ok": 12,
        "ko": 0
    },
    "maxResponseTime": {
        "total": 9277,
        "ok": 9277,
        "ko": 0
    },
    "meanResponseTime": {
        "total": 241,
        "ok": 241,
        "ko": 0
    },
    "standardDeviation": {
        "total": 1038,
        "ok": 1038,
        "ko": 0
    },
    "percentiles1": {
        "total": 17,
        "ok": 17,
        "ko": 0
    },
    "percentiles2": {
        "total": 47,
        "ok": 47,
        "ko": 0
    },
    "percentiles3": {
        "total": 834,
        "ok": 834,
        "ko": 0
    },
    "percentiles4": {
        "total": 6267,
        "ok": 6267,
        "ko": 0
    },
    "group1": {
    "name": "t < 800 ms",
    "count": 685,
    "percentage": 95
},
    "group2": {
    "name": "800 ms < t < 1200 ms",
    "count": 4,
    "percentage": 1
},
    "group3": {
    "name": "t > 1200 ms",
    "count": 33,
    "percentage": 5
},
    "group4": {
    "name": "failed",
    "count": 0,
    "percentage": 0
},
    "meanNumberOfRequestsPerSecond": {
        "total": 0.30083333333333334,
        "ok": 0.30083333333333334,
        "ko": 0
    }
}
    },"req_01-02-admin-por-d2069": {
        "type": "REQUEST",
        "name": "01.02.Admin.Portal.Home",
"path": "01.02.Admin.Portal.Home",
"pathFormatted": "req_01-02-admin-por-d2069",
"stats": {
    "name": "01.02.Admin.Portal.Home",
    "numberOfRequests": {
        "total": 722,
        "ok": 722,
        "ko": 0
    },
    "minResponseTime": {
        "total": 32,
        "ok": 32,
        "ko": 0
    },
    "maxResponseTime": {
        "total": 240,
        "ok": 240,
        "ko": 0
    },
    "meanResponseTime": {
        "total": 50,
        "ok": 50,
        "ko": 0
    },
    "standardDeviation": {
        "total": 26,
        "ok": 26,
        "ko": 0
    },
    "percentiles1": {
        "total": 42,
        "ok": 42,
        "ko": 0
    },
    "percentiles2": {
        "total": 49,
        "ok": 49,
        "ko": 0
    },
    "percentiles3": {
        "total": 126,
        "ok": 126,
        "ko": 0
    },
    "percentiles4": {
        "total": 140,
        "ok": 140,
        "ko": 0
    },
    "group1": {
    "name": "t < 800 ms",
    "count": 722,
    "percentage": 100
},
    "group2": {
    "name": "800 ms < t < 1200 ms",
    "count": 0,
    "percentage": 0
},
    "group3": {
    "name": "t > 1200 ms",
    "count": 0,
    "percentage": 0
},
    "group4": {
    "name": "failed",
    "count": 0,
    "percentage": 0
},
    "meanNumberOfRequestsPerSecond": {
        "total": 0.30083333333333334,
        "ok": 0.30083333333333334,
        "ko": 0
    }
}
    },"req_01-03-admin-por-c82a9": {
        "type": "REQUEST",
        "name": "01.03.Admin.Portal.Home",
"path": "01.03.Admin.Portal.Home",
"pathFormatted": "req_01-03-admin-por-c82a9",
"stats": {
    "name": "01.03.Admin.Portal.Home",
    "numberOfRequests": {
        "total": 722,
        "ok": 722,
        "ko": 0
    },
    "minResponseTime": {
        "total": 101,
        "ok": 101,
        "ko": 0
    },
    "maxResponseTime": {
        "total": 737,
        "ok": 737,
        "ko": 0
    },
    "meanResponseTime": {
        "total": 336,
        "ok": 336,
        "ko": 0
    },
    "standardDeviation": {
        "total": 85,
        "ok": 85,
        "ko": 0
    },
    "percentiles1": {
        "total": 312,
        "ok": 312,
        "ko": 0
    },
    "percentiles2": {
        "total": 357,
        "ok": 357,
        "ko": 0
    },
    "percentiles3": {
        "total": 487,
        "ok": 487,
        "ko": 0
    },
    "percentiles4": {
        "total": 568,
        "ok": 568,
        "ko": 0
    },
    "group1": {
    "name": "t < 800 ms",
    "count": 722,
    "percentage": 100
},
    "group2": {
    "name": "800 ms < t < 1200 ms",
    "count": 0,
    "percentage": 0
},
    "group3": {
    "name": "t > 1200 ms",
    "count": 0,
    "percentage": 0
},
    "group4": {
    "name": "failed",
    "count": 0,
    "percentage": 0
},
    "meanNumberOfRequestsPerSecond": {
        "total": 0.30083333333333334,
        "ok": 0.30083333333333334,
        "ko": 0
    }
}
    },"req_01-04-admin-por-d2c6f": {
        "type": "REQUEST",
        "name": "01.04.Admin.Portal.Home",
"path": "01.04.Admin.Portal.Home",
"pathFormatted": "req_01-04-admin-por-d2c6f",
"stats": {
    "name": "01.04.Admin.Portal.Home",
    "numberOfRequests": {
        "total": 722,
        "ok": 722,
        "ko": 0
    },
    "minResponseTime": {
        "total": 203,
        "ok": 203,
        "ko": 0
    },
    "maxResponseTime": {
        "total": 452,
        "ok": 452,
        "ko": 0
    },
    "meanResponseTime": {
        "total": 229,
        "ok": 229,
        "ko": 0
    },
    "standardDeviation": {
        "total": 31,
        "ok": 31,
        "ko": 0
    },
    "percentiles1": {
        "total": 222,
        "ok": 222,
        "ko": 0
    },
    "percentiles2": {
        "total": 227,
        "ok": 227,
        "ko": 0
    },
    "percentiles3": {
        "total": 257,
        "ok": 257,
        "ko": 0
    },
    "percentiles4": {
        "total": 408,
        "ok": 408,
        "ko": 0
    },
    "group1": {
    "name": "t < 800 ms",
    "count": 722,
    "percentage": 100
},
    "group2": {
    "name": "800 ms < t < 1200 ms",
    "count": 0,
    "percentage": 0
},
    "group3": {
    "name": "t > 1200 ms",
    "count": 0,
    "percentage": 0
},
    "group4": {
    "name": "failed",
    "count": 0,
    "percentage": 0
},
    "meanNumberOfRequestsPerSecond": {
        "total": 0.30083333333333334,
        "ok": 0.30083333333333334,
        "ko": 0
    }
}
    },"req_02-00-admin-por-64e11": {
        "type": "REQUEST",
        "name": "02.00.Admin.Portal.Login",
"path": "02.00.Admin.Portal.Login",
"pathFormatted": "req_02-00-admin-por-64e11",
"stats": {
    "name": "02.00.Admin.Portal.Login",
    "numberOfRequests": {
        "total": 722,
        "ok": 719,
        "ko": 3
    },
    "minResponseTime": {
        "total": 142,
        "ok": 142,
        "ko": 359
    },
    "maxResponseTime": {
        "total": 1382,
        "ok": 1382,
        "ko": 447
    },
    "meanResponseTime": {
        "total": 244,
        "ok": 244,
        "ko": 396
    },
    "standardDeviation": {
        "total": 113,
        "ok": 112,
        "ko": 37
    },
    "percentiles1": {
        "total": 196,
        "ok": 196,
        "ko": 381
    },
    "percentiles2": {
        "total": 259,
        "ok": 258,
        "ko": 414
    },
    "percentiles3": {
        "total": 453,
        "ok": 453,
        "ko": 440
    },
    "percentiles4": {
        "total": 590,
        "ok": 590,
        "ko": 446
    },
    "group1": {
    "name": "t < 800 ms",
    "count": 718,
    "percentage": 99
},
    "group2": {
    "name": "800 ms < t < 1200 ms",
    "count": 0,
    "percentage": 0
},
    "group3": {
    "name": "t > 1200 ms",
    "count": 1,
    "percentage": 0
},
    "group4": {
    "name": "failed",
    "count": 3,
    "percentage": 0
},
    "meanNumberOfRequestsPerSecond": {
        "total": 0.30083333333333334,
        "ok": 0.2995833333333333,
        "ko": 0.00125
    }
}
    },"req_04-01-admin-por-2574b": {
        "type": "REQUEST",
        "name": "04.01.Admin.Portal.Questnnaire",
"path": "04.01.Admin.Portal.Questnnaire",
"pathFormatted": "req_04-01-admin-por-2574b",
"stats": {
    "name": "04.01.Admin.Portal.Questnnaire",
    "numberOfRequests": {
        "total": 722,
        "ok": 722,
        "ko": 0
    },
    "minResponseTime": {
        "total": 14,
        "ok": 14,
        "ko": 0
    },
    "maxResponseTime": {
        "total": 8913,
        "ok": 8913,
        "ko": 0
    },
    "meanResponseTime": {
        "total": 496,
        "ok": 496,
        "ko": 0
    },
    "standardDeviation": {
        "total": 868,
        "ok": 868,
        "ko": 0
    },
    "percentiles1": {
        "total": 270,
        "ok": 270,
        "ko": 0
    },
    "percentiles2": {
        "total": 355,
        "ok": 355,
        "ko": 0
    },
    "percentiles3": {
        "total": 1520,
        "ok": 1520,
        "ko": 0
    },
    "percentiles4": {
        "total": 5264,
        "ok": 5264,
        "ko": 0
    },
    "group1": {
    "name": "t < 800 ms",
    "count": 658,
    "percentage": 91
},
    "group2": {
    "name": "800 ms < t < 1200 ms",
    "count": 15,
    "percentage": 2
},
    "group3": {
    "name": "t > 1200 ms",
    "count": 49,
    "percentage": 7
},
    "group4": {
    "name": "failed",
    "count": 0,
    "percentage": 0
},
    "meanNumberOfRequestsPerSecond": {
        "total": 0.30083333333333334,
        "ok": 0.30083333333333334,
        "ko": 0
    }
}
    },"req_04-02-admin-por-71142": {
        "type": "REQUEST",
        "name": "04.02.Admin.Portal.Questnnaire",
"path": "04.02.Admin.Portal.Questnnaire",
"pathFormatted": "req_04-02-admin-por-71142",
"stats": {
    "name": "04.02.Admin.Portal.Questnnaire",
    "numberOfRequests": {
        "total": 722,
        "ok": 721,
        "ko": 1
    },
    "minResponseTime": {
        "total": 122,
        "ok": 122,
        "ko": 20010
    },
    "maxResponseTime": {
        "total": 20010,
        "ok": 16256,
        "ko": 20010
    },
    "meanResponseTime": {
        "total": 1324,
        "ok": 1298,
        "ko": 20010
    },
    "standardDeviation": {
        "total": 2583,
        "ok": 2489,
        "ko": 0
    },
    "percentiles1": {
        "total": 256,
        "ok": 255,
        "ko": 20010
    },
    "percentiles2": {
        "total": 887,
        "ok": 875,
        "ko": 20010
    },
    "percentiles3": {
        "total": 6827,
        "ok": 6822,
        "ko": 20010
    },
    "percentiles4": {
        "total": 12244,
        "ok": 11877,
        "ko": 20010
    },
    "group1": {
    "name": "t < 800 ms",
    "count": 528,
    "percentage": 73
},
    "group2": {
    "name": "800 ms < t < 1200 ms",
    "count": 39,
    "percentage": 5
},
    "group3": {
    "name": "t > 1200 ms",
    "count": 154,
    "percentage": 21
},
    "group4": {
    "name": "failed",
    "count": 1,
    "percentage": 0
},
    "meanNumberOfRequestsPerSecond": {
        "total": 0.30083333333333334,
        "ok": 0.30041666666666667,
        "ko": 4.166666666666667E-4
    }
}
    },"req_04-03-admin-por-832e4": {
        "type": "REQUEST",
        "name": "04.03.Admin.Portal.Questnnaire",
"path": "04.03.Admin.Portal.Questnnaire",
"pathFormatted": "req_04-03-admin-por-832e4",
"stats": {
    "name": "04.03.Admin.Portal.Questnnaire",
    "numberOfRequests": {
        "total": 722,
        "ok": 722,
        "ko": 0
    },
    "minResponseTime": {
        "total": 46,
        "ok": 46,
        "ko": 0
    },
    "maxResponseTime": {
        "total": 1795,
        "ok": 1795,
        "ko": 0
    },
    "meanResponseTime": {
        "total": 395,
        "ok": 395,
        "ko": 0
    },
    "standardDeviation": {
        "total": 196,
        "ok": 196,
        "ko": 0
    },
    "percentiles1": {
        "total": 383,
        "ok": 383,
        "ko": 0
    },
    "percentiles2": {
        "total": 549,
        "ok": 549,
        "ko": 0
    },
    "percentiles3": {
        "total": 679,
        "ok": 679,
        "ko": 0
    },
    "percentiles4": {
        "total": 819,
        "ok": 819,
        "ko": 0
    },
    "group1": {
    "name": "t < 800 ms",
    "count": 712,
    "percentage": 99
},
    "group2": {
    "name": "800 ms < t < 1200 ms",
    "count": 9,
    "percentage": 1
},
    "group3": {
    "name": "t > 1200 ms",
    "count": 1,
    "percentage": 0
},
    "group4": {
    "name": "failed",
    "count": 0,
    "percentage": 0
},
    "meanNumberOfRequestsPerSecond": {
        "total": 0.30083333333333334,
        "ok": 0.30083333333333334,
        "ko": 0
    }
}
    },"req_04-04-admin-por-a4a70": {
        "type": "REQUEST",
        "name": "04.04.Admin.Portal.Questnnaire",
"path": "04.04.Admin.Portal.Questnnaire",
"pathFormatted": "req_04-04-admin-por-a4a70",
"stats": {
    "name": "04.04.Admin.Portal.Questnnaire",
    "numberOfRequests": {
        "total": 719,
        "ok": 719,
        "ko": 0
    },
    "minResponseTime": {
        "total": 49,
        "ok": 49,
        "ko": 0
    },
    "maxResponseTime": {
        "total": 1119,
        "ok": 1119,
        "ko": 0
    },
    "meanResponseTime": {
        "total": 432,
        "ok": 432,
        "ko": 0
    },
    "standardDeviation": {
        "total": 177,
        "ok": 177,
        "ko": 0
    },
    "percentiles1": {
        "total": 464,
        "ok": 464,
        "ko": 0
    },
    "percentiles2": {
        "total": 553,
        "ok": 553,
        "ko": 0
    },
    "percentiles3": {
        "total": 676,
        "ok": 676,
        "ko": 0
    },
    "percentiles4": {
        "total": 841,
        "ok": 841,
        "ko": 0
    },
    "group1": {
    "name": "t < 800 ms",
    "count": 709,
    "percentage": 99
},
    "group2": {
    "name": "800 ms < t < 1200 ms",
    "count": 10,
    "percentage": 1
},
    "group3": {
    "name": "t > 1200 ms",
    "count": 0,
    "percentage": 0
},
    "group4": {
    "name": "failed",
    "count": 0,
    "percentage": 0
},
    "meanNumberOfRequestsPerSecond": {
        "total": 0.2995833333333333,
        "ok": 0.2995833333333333,
        "ko": 0
    }
}
    },"req_05-01-admin-por-d870b": {
        "type": "REQUEST",
        "name": "05.01.Admin.Portal.Back2Dashboard",
"path": "05.01.Admin.Portal.Back2Dashboard",
"pathFormatted": "req_05-01-admin-por-d870b",
"stats": {
    "name": "05.01.Admin.Portal.Back2Dashboard",
    "numberOfRequests": {
        "total": 719,
        "ok": 719,
        "ko": 0
    },
    "minResponseTime": {
        "total": 12,
        "ok": 12,
        "ko": 0
    },
    "maxResponseTime": {
        "total": 8984,
        "ok": 8984,
        "ko": 0
    },
    "meanResponseTime": {
        "total": 260,
        "ok": 260,
        "ko": 0
    },
    "standardDeviation": {
        "total": 842,
        "ok": 842,
        "ko": 0
    },
    "percentiles1": {
        "total": 18,
        "ok": 18,
        "ko": 0
    },
    "percentiles2": {
        "total": 51,
        "ok": 51,
        "ko": 0
    },
    "percentiles3": {
        "total": 1284,
        "ok": 1284,
        "ko": 0
    },
    "percentiles4": {
        "total": 4986,
        "ok": 4986,
        "ko": 0
    },
    "group1": {
    "name": "t < 800 ms",
    "count": 653,
    "percentage": 91
},
    "group2": {
    "name": "800 ms < t < 1200 ms",
    "count": 21,
    "percentage": 3
},
    "group3": {
    "name": "t > 1200 ms",
    "count": 45,
    "percentage": 6
},
    "group4": {
    "name": "failed",
    "count": 0,
    "percentage": 0
},
    "meanNumberOfRequestsPerSecond": {
        "total": 0.2995833333333333,
        "ok": 0.2995833333333333,
        "ko": 0
    }
}
    },"req_05-02-admin-por-316fc": {
        "type": "REQUEST",
        "name": "05.02.Admin.Portal.Back2Dashboard",
"path": "05.02.Admin.Portal.Back2Dashboard",
"pathFormatted": "req_05-02-admin-por-316fc",
"stats": {
    "name": "05.02.Admin.Portal.Back2Dashboard",
    "numberOfRequests": {
        "total": 719,
        "ok": 719,
        "ko": 0
    },
    "minResponseTime": {
        "total": 12,
        "ok": 12,
        "ko": 0
    },
    "maxResponseTime": {
        "total": 7979,
        "ok": 7979,
        "ko": 0
    },
    "meanResponseTime": {
        "total": 140,
        "ok": 140,
        "ko": 0
    },
    "standardDeviation": {
        "total": 650,
        "ok": 650,
        "ko": 0
    },
    "percentiles1": {
        "total": 16,
        "ok": 16,
        "ko": 0
    },
    "percentiles2": {
        "total": 21,
        "ok": 21,
        "ko": 0
    },
    "percentiles3": {
        "total": 305,
        "ok": 305,
        "ko": 0
    },
    "percentiles4": {
        "total": 3648,
        "ok": 3648,
        "ko": 0
    },
    "group1": {
    "name": "t < 800 ms",
    "count": 693,
    "percentage": 96
},
    "group2": {
    "name": "800 ms < t < 1200 ms",
    "count": 3,
    "percentage": 0
},
    "group3": {
    "name": "t > 1200 ms",
    "count": 23,
    "percentage": 3
},
    "group4": {
    "name": "failed",
    "count": 0,
    "percentage": 0
},
    "meanNumberOfRequestsPerSecond": {
        "total": 0.2995833333333333,
        "ok": 0.2995833333333333,
        "ko": 0
    }
}
    },"req_05-03-admin-por-06952": {
        "type": "REQUEST",
        "name": "05.03.Admin.Portal.Back2Dashboard",
"path": "05.03.Admin.Portal.Back2Dashboard",
"pathFormatted": "req_05-03-admin-por-06952",
"stats": {
    "name": "05.03.Admin.Portal.Back2Dashboard",
    "numberOfRequests": {
        "total": 719,
        "ok": 719,
        "ko": 0
    },
    "minResponseTime": {
        "total": 60,
        "ok": 60,
        "ko": 0
    },
    "maxResponseTime": {
        "total": 1021,
        "ok": 1021,
        "ko": 0
    },
    "meanResponseTime": {
        "total": 427,
        "ok": 427,
        "ko": 0
    },
    "standardDeviation": {
        "total": 183,
        "ok": 183,
        "ko": 0
    },
    "percentiles1": {
        "total": 445,
        "ok": 445,
        "ko": 0
    },
    "percentiles2": {
        "total": 571,
        "ok": 571,
        "ko": 0
    },
    "percentiles3": {
        "total": 681,
        "ok": 681,
        "ko": 0
    },
    "percentiles4": {
        "total": 869,
        "ok": 869,
        "ko": 0
    },
    "group1": {
    "name": "t < 800 ms",
    "count": 706,
    "percentage": 98
},
    "group2": {
    "name": "800 ms < t < 1200 ms",
    "count": 13,
    "percentage": 2
},
    "group3": {
    "name": "t > 1200 ms",
    "count": 0,
    "percentage": 0
},
    "group4": {
    "name": "failed",
    "count": 0,
    "percentage": 0
},
    "meanNumberOfRequestsPerSecond": {
        "total": 0.2995833333333333,
        "ok": 0.2995833333333333,
        "ko": 0
    }
}
    },"req_06-01-admin-por-f292a": {
        "type": "REQUEST",
        "name": "06.01.Admin.Portal.BookHearing",
"path": "06.01.Admin.Portal.BookHearing",
"pathFormatted": "req_06-01-admin-por-f292a",
"stats": {
    "name": "06.01.Admin.Portal.BookHearing",
    "numberOfRequests": {
        "total": 719,
        "ok": 719,
        "ko": 0
    },
    "minResponseTime": {
        "total": 12,
        "ok": 12,
        "ko": 0
    },
    "maxResponseTime": {
        "total": 9226,
        "ok": 9226,
        "ko": 0
    },
    "meanResponseTime": {
        "total": 126,
        "ok": 126,
        "ko": 0
    },
    "standardDeviation": {
        "total": 683,
        "ok": 683,
        "ko": 0
    },
    "percentiles1": {
        "total": 17,
        "ok": 17,
        "ko": 0
    },
    "percentiles2": {
        "total": 25,
        "ok": 25,
        "ko": 0
    },
    "percentiles3": {
        "total": 233,
        "ok": 233,
        "ko": 0
    },
    "percentiles4": {
        "total": 2645,
        "ok": 2645,
        "ko": 0
    },
    "group1": {
    "name": "t < 800 ms",
    "count": 702,
    "percentage": 98
},
    "group2": {
    "name": "800 ms < t < 1200 ms",
    "count": 5,
    "percentage": 1
},
    "group3": {
    "name": "t > 1200 ms",
    "count": 12,
    "percentage": 2
},
    "group4": {
    "name": "failed",
    "count": 0,
    "percentage": 0
},
    "meanNumberOfRequestsPerSecond": {
        "total": 0.2995833333333333,
        "ok": 0.2995833333333333,
        "ko": 0
    }
}
    },"req_06-02-admin-por-88d79": {
        "type": "REQUEST",
        "name": "06.02.Admin.Portal.BookHearing",
"path": "06.02.Admin.Portal.BookHearing",
"pathFormatted": "req_06-02-admin-por-88d79",
"stats": {
    "name": "06.02.Admin.Portal.BookHearing",
    "numberOfRequests": {
        "total": 719,
        "ok": 719,
        "ko": 0
    },
    "minResponseTime": {
        "total": 19,
        "ok": 19,
        "ko": 0
    },
    "maxResponseTime": {
        "total": 11535,
        "ok": 11535,
        "ko": 0
    },
    "meanResponseTime": {
        "total": 297,
        "ok": 297,
        "ko": 0
    },
    "standardDeviation": {
        "total": 1144,
        "ok": 1144,
        "ko": 0
    },
    "percentiles1": {
        "total": 27,
        "ok": 27,
        "ko": 0
    },
    "percentiles2": {
        "total": 66,
        "ok": 66,
        "ko": 0
    },
    "percentiles3": {
        "total": 1627,
        "ok": 1627,
        "ko": 0
    },
    "percentiles4": {
        "total": 5556,
        "ok": 5556,
        "ko": 0
    },
    "group1": {
    "name": "t < 800 ms",
    "count": 670,
    "percentage": 93
},
    "group2": {
    "name": "800 ms < t < 1200 ms",
    "count": 10,
    "percentage": 1
},
    "group3": {
    "name": "t > 1200 ms",
    "count": 39,
    "percentage": 5
},
    "group4": {
    "name": "failed",
    "count": 0,
    "percentage": 0
},
    "meanNumberOfRequestsPerSecond": {
        "total": 0.2995833333333333,
        "ok": 0.2995833333333333,
        "ko": 0
    }
}
    },"req_06-03-admin-por-957cd": {
        "type": "REQUEST",
        "name": "06.03.Admin.Portal.BookHearing",
"path": "06.03.Admin.Portal.BookHearing",
"pathFormatted": "req_06-03-admin-por-957cd",
"stats": {
    "name": "06.03.Admin.Portal.BookHearing",
    "numberOfRequests": {
        "total": 719,
        "ok": 719,
        "ko": 0
    },
    "minResponseTime": {
        "total": 60,
        "ok": 60,
        "ko": 0
    },
    "maxResponseTime": {
        "total": 899,
        "ok": 899,
        "ko": 0
    },
    "meanResponseTime": {
        "total": 425,
        "ok": 425,
        "ko": 0
    },
    "standardDeviation": {
        "total": 176,
        "ok": 176,
        "ko": 0
    },
    "percentiles1": {
        "total": 447,
        "ok": 447,
        "ko": 0
    },
    "percentiles2": {
        "total": 562,
        "ok": 562,
        "ko": 0
    },
    "percentiles3": {
        "total": 672,
        "ok": 672,
        "ko": 0
    },
    "percentiles4": {
        "total": 811,
        "ok": 811,
        "ko": 0
    },
    "group1": {
    "name": "t < 800 ms",
    "count": 711,
    "percentage": 99
},
    "group2": {
    "name": "800 ms < t < 1200 ms",
    "count": 8,
    "percentage": 1
},
    "group3": {
    "name": "t > 1200 ms",
    "count": 0,
    "percentage": 0
},
    "group4": {
    "name": "failed",
    "count": 0,
    "percentage": 0
},
    "meanNumberOfRequestsPerSecond": {
        "total": 0.2995833333333333,
        "ok": 0.2995833333333333,
        "ko": 0
    }
}
    },"req_07-01-admin-por-e6486": {
        "type": "REQUEST",
        "name": "07.01.Admin.Portal.HearingDetails",
"path": "07.01.Admin.Portal.HearingDetails",
"pathFormatted": "req_07-01-admin-por-e6486",
"stats": {
    "name": "07.01.Admin.Portal.HearingDetails",
    "numberOfRequests": {
        "total": 719,
        "ok": 719,
        "ko": 0
    },
    "minResponseTime": {
        "total": 12,
        "ok": 12,
        "ko": 0
    },
    "maxResponseTime": {
        "total": 7091,
        "ok": 7091,
        "ko": 0
    },
    "meanResponseTime": {
        "total": 135,
        "ok": 135,
        "ko": 0
    },
    "standardDeviation": {
        "total": 682,
        "ok": 682,
        "ko": 0
    },
    "percentiles1": {
        "total": 17,
        "ok": 17,
        "ko": 0
    },
    "percentiles2": {
        "total": 27,
        "ok": 27,
        "ko": 0
    },
    "percentiles3": {
        "total": 318,
        "ok": 318,
        "ko": 0
    },
    "percentiles4": {
        "total": 4279,
        "ok": 4279,
        "ko": 0
    },
    "group1": {
    "name": "t < 800 ms",
    "count": 702,
    "percentage": 98
},
    "group2": {
    "name": "800 ms < t < 1200 ms",
    "count": 4,
    "percentage": 1
},
    "group3": {
    "name": "t > 1200 ms",
    "count": 13,
    "percentage": 2
},
    "group4": {
    "name": "failed",
    "count": 0,
    "percentage": 0
},
    "meanNumberOfRequestsPerSecond": {
        "total": 0.2995833333333333,
        "ok": 0.2995833333333333,
        "ko": 0
    }
}
    },"req_07-02-admin-por-f7164": {
        "type": "REQUEST",
        "name": "07.02.Admin.Portal.HearingDetails",
"path": "07.02.Admin.Portal.HearingDetails",
"pathFormatted": "req_07-02-admin-por-f7164",
"stats": {
    "name": "07.02.Admin.Portal.HearingDetails",
    "numberOfRequests": {
        "total": 717,
        "ok": 717,
        "ko": 0
    },
    "minResponseTime": {
        "total": 18,
        "ok": 18,
        "ko": 0
    },
    "maxResponseTime": {
        "total": 12675,
        "ok": 12675,
        "ko": 0
    },
    "meanResponseTime": {
        "total": 514,
        "ok": 514,
        "ko": 0
    },
    "standardDeviation": {
        "total": 1559,
        "ok": 1559,
        "ko": 0
    },
    "percentiles1": {
        "total": 30,
        "ok": 30,
        "ko": 0
    },
    "percentiles2": {
        "total": 90,
        "ok": 90,
        "ko": 0
    },
    "percentiles3": {
        "total": 3574,
        "ok": 3574,
        "ko": 0
    },
    "percentiles4": {
        "total": 7891,
        "ok": 7891,
        "ko": 0
    },
    "group1": {
    "name": "t < 800 ms",
    "count": 632,
    "percentage": 88
},
    "group2": {
    "name": "800 ms < t < 1200 ms",
    "count": 7,
    "percentage": 1
},
    "group3": {
    "name": "t > 1200 ms",
    "count": 78,
    "percentage": 11
},
    "group4": {
    "name": "failed",
    "count": 0,
    "percentage": 0
},
    "meanNumberOfRequestsPerSecond": {
        "total": 0.29875,
        "ok": 0.29875,
        "ko": 0
    }
}
    },"req_07-03-admin-por-9cec0": {
        "type": "REQUEST",
        "name": "07.03.Admin.Portal.HearingDetails",
"path": "07.03.Admin.Portal.HearingDetails",
"pathFormatted": "req_07-03-admin-por-9cec0",
"stats": {
    "name": "07.03.Admin.Portal.HearingDetails",
    "numberOfRequests": {
        "total": 715,
        "ok": 715,
        "ko": 0
    },
    "minResponseTime": {
        "total": 55,
        "ok": 55,
        "ko": 0
    },
    "maxResponseTime": {
        "total": 4889,
        "ok": 4889,
        "ko": 0
    },
    "meanResponseTime": {
        "total": 388,
        "ok": 388,
        "ko": 0
    },
    "standardDeviation": {
        "total": 255,
        "ok": 255,
        "ko": 0
    },
    "percentiles1": {
        "total": 349,
        "ok": 349,
        "ko": 0
    },
    "percentiles2": {
        "total": 533,
        "ok": 533,
        "ko": 0
    },
    "percentiles3": {
        "total": 675,
        "ok": 675,
        "ko": 0
    },
    "percentiles4": {
        "total": 822,
        "ok": 822,
        "ko": 0
    },
    "group1": {
    "name": "t < 800 ms",
    "count": 706,
    "percentage": 99
},
    "group2": {
    "name": "800 ms < t < 1200 ms",
    "count": 6,
    "percentage": 1
},
    "group3": {
    "name": "t > 1200 ms",
    "count": 3,
    "percentage": 0
},
    "group4": {
    "name": "failed",
    "count": 0,
    "percentage": 0
},
    "meanNumberOfRequestsPerSecond": {
        "total": 0.29791666666666666,
        "ok": 0.29791666666666666,
        "ko": 0
    }
}
    },"req_07-04-admin-por-d533c": {
        "type": "REQUEST",
        "name": "07.04.Admin.Portal.HearingDetails",
"path": "07.04.Admin.Portal.HearingDetails",
"pathFormatted": "req_07-04-admin-por-d533c",
"stats": {
    "name": "07.04.Admin.Portal.HearingDetails",
    "numberOfRequests": {
        "total": 713,
        "ok": 713,
        "ko": 0
    },
    "minResponseTime": {
        "total": 49,
        "ok": 49,
        "ko": 0
    },
    "maxResponseTime": {
        "total": 1378,
        "ok": 1378,
        "ko": 0
    },
    "meanResponseTime": {
        "total": 371,
        "ok": 371,
        "ko": 0
    },
    "standardDeviation": {
        "total": 180,
        "ok": 180,
        "ko": 0
    },
    "percentiles1": {
        "total": 328,
        "ok": 328,
        "ko": 0
    },
    "percentiles2": {
        "total": 504,
        "ok": 505,
        "ko": 0
    },
    "percentiles3": {
        "total": 674,
        "ok": 674,
        "ko": 0
    },
    "percentiles4": {
        "total": 805,
        "ok": 805,
        "ko": 0
    },
    "group1": {
    "name": "t < 800 ms",
    "count": 705,
    "percentage": 99
},
    "group2": {
    "name": "800 ms < t < 1200 ms",
    "count": 7,
    "percentage": 1
},
    "group3": {
    "name": "t > 1200 ms",
    "count": 1,
    "percentage": 0
},
    "group4": {
    "name": "failed",
    "count": 0,
    "percentage": 0
},
    "meanNumberOfRequestsPerSecond": {
        "total": 0.2970833333333333,
        "ok": 0.2970833333333333,
        "ko": 0
    }
}
    },"req_08-01-admin-por-0079f": {
        "type": "REQUEST",
        "name": "08.01.Admin.Portal.HearingSchedule",
"path": "08.01.Admin.Portal.HearingSchedule",
"pathFormatted": "req_08-01-admin-por-0079f",
"stats": {
    "name": "08.01.Admin.Portal.HearingSchedule",
    "numberOfRequests": {
        "total": 713,
        "ok": 713,
        "ko": 0
    },
    "minResponseTime": {
        "total": 13,
        "ok": 13,
        "ko": 0
    },
    "maxResponseTime": {
        "total": 7790,
        "ok": 7790,
        "ko": 0
    },
    "meanResponseTime": {
        "total": 223,
        "ok": 223,
        "ko": 0
    },
    "standardDeviation": {
        "total": 692,
        "ok": 692,
        "ko": 0
    },
    "percentiles1": {
        "total": 18,
        "ok": 18,
        "ko": 0
    },
    "percentiles2": {
        "total": 44,
        "ok": 44,
        "ko": 0
    },
    "percentiles3": {
        "total": 1769,
        "ok": 1769,
        "ko": 0
    },
    "percentiles4": {
        "total": 3279,
        "ok": 3279,
        "ko": 0
    },
    "group1": {
    "name": "t < 800 ms",
    "count": 661,
    "percentage": 93
},
    "group2": {
    "name": "800 ms < t < 1200 ms",
    "count": 8,
    "percentage": 1
},
    "group3": {
    "name": "t > 1200 ms",
    "count": 44,
    "percentage": 6
},
    "group4": {
    "name": "failed",
    "count": 0,
    "percentage": 0
},
    "meanNumberOfRequestsPerSecond": {
        "total": 0.2970833333333333,
        "ok": 0.2970833333333333,
        "ko": 0
    }
}
    },"req_08-02-admin-por-35feb": {
        "type": "REQUEST",
        "name": "08.02.Admin.Portal.HearingSchedule",
"path": "08.02.Admin.Portal.HearingSchedule",
"pathFormatted": "req_08-02-admin-por-35feb",
"stats": {
    "name": "08.02.Admin.Portal.HearingSchedule",
    "numberOfRequests": {
        "total": 711,
        "ok": 711,
        "ko": 0
    },
    "minResponseTime": {
        "total": 2252,
        "ok": 2252,
        "ko": 0
    },
    "maxResponseTime": {
        "total": 19554,
        "ok": 19554,
        "ko": 0
    },
    "meanResponseTime": {
        "total": 4089,
        "ok": 4089,
        "ko": 0
    },
    "standardDeviation": {
        "total": 3169,
        "ok": 3169,
        "ko": 0
    },
    "percentiles1": {
        "total": 2855,
        "ok": 2855,
        "ko": 0
    },
    "percentiles2": {
        "total": 3750,
        "ok": 3750,
        "ko": 0
    },
    "percentiles3": {
        "total": 12758,
        "ok": 12758,
        "ko": 0
    },
    "percentiles4": {
        "total": 18334,
        "ok": 18334,
        "ko": 0
    },
    "group1": {
    "name": "t < 800 ms",
    "count": 0,
    "percentage": 0
},
    "group2": {
    "name": "800 ms < t < 1200 ms",
    "count": 0,
    "percentage": 0
},
    "group3": {
    "name": "t > 1200 ms",
    "count": 711,
    "percentage": 100
},
    "group4": {
    "name": "failed",
    "count": 0,
    "percentage": 0
},
    "meanNumberOfRequestsPerSecond": {
        "total": 0.29625,
        "ok": 0.29625,
        "ko": 0
    }
}
    },"req_08-03-admin-por-ea567": {
        "type": "REQUEST",
        "name": "08.03.Admin.Portal.HearingSchedule",
"path": "08.03.Admin.Portal.HearingSchedule",
"pathFormatted": "req_08-03-admin-por-ea567",
"stats": {
    "name": "08.03.Admin.Portal.HearingSchedule",
    "numberOfRequests": {
        "total": 711,
        "ok": 711,
        "ko": 0
    },
    "minResponseTime": {
        "total": 46,
        "ok": 46,
        "ko": 0
    },
    "maxResponseTime": {
        "total": 984,
        "ok": 984,
        "ko": 0
    },
    "meanResponseTime": {
        "total": 412,
        "ok": 412,
        "ko": 0
    },
    "standardDeviation": {
        "total": 189,
        "ok": 189,
        "ko": 0
    },
    "percentiles1": {
        "total": 413,
        "ok": 413,
        "ko": 0
    },
    "percentiles2": {
        "total": 575,
        "ok": 575,
        "ko": 0
    },
    "percentiles3": {
        "total": 694,
        "ok": 694,
        "ko": 0
    },
    "percentiles4": {
        "total": 784,
        "ok": 784,
        "ko": 0
    },
    "group1": {
    "name": "t < 800 ms",
    "count": 707,
    "percentage": 99
},
    "group2": {
    "name": "800 ms < t < 1200 ms",
    "count": 4,
    "percentage": 1
},
    "group3": {
    "name": "t > 1200 ms",
    "count": 0,
    "percentage": 0
},
    "group4": {
    "name": "failed",
    "count": 0,
    "percentage": 0
},
    "meanNumberOfRequestsPerSecond": {
        "total": 0.29625,
        "ok": 0.29625,
        "ko": 0
    }
}
    },"req_08-04-admin-por-55c31": {
        "type": "REQUEST",
        "name": "08.04.Admin.Portal.HearingSchedule",
"path": "08.04.Admin.Portal.HearingSchedule",
"pathFormatted": "req_08-04-admin-por-55c31",
"stats": {
    "name": "08.04.Admin.Portal.HearingSchedule",
    "numberOfRequests": {
        "total": 711,
        "ok": 711,
        "ko": 0
    },
    "minResponseTime": {
        "total": 47,
        "ok": 47,
        "ko": 0
    },
    "maxResponseTime": {
        "total": 1528,
        "ok": 1528,
        "ko": 0
    },
    "meanResponseTime": {
        "total": 372,
        "ok": 372,
        "ko": 0
    },
    "standardDeviation": {
        "total": 180,
        "ok": 180,
        "ko": 0
    },
    "percentiles1": {
        "total": 334,
        "ok": 334,
        "ko": 0
    },
    "percentiles2": {
        "total": 494,
        "ok": 494,
        "ko": 0
    },
    "percentiles3": {
        "total": 684,
        "ok": 684,
        "ko": 0
    },
    "percentiles4": {
        "total": 787,
        "ok": 787,
        "ko": 0
    },
    "group1": {
    "name": "t < 800 ms",
    "count": 706,
    "percentage": 99
},
    "group2": {
    "name": "800 ms < t < 1200 ms",
    "count": 4,
    "percentage": 1
},
    "group3": {
    "name": "t > 1200 ms",
    "count": 1,
    "percentage": 0
},
    "group4": {
    "name": "failed",
    "count": 0,
    "percentage": 0
},
    "meanNumberOfRequestsPerSecond": {
        "total": 0.29625,
        "ok": 0.29625,
        "ko": 0
    }
}
    },"req_09-01-admin-por-1f196": {
        "type": "REQUEST",
        "name": "09.01.Admin.Portal.AssignJudge",
"path": "09.01.Admin.Portal.AssignJudge",
"pathFormatted": "req_09-01-admin-por-1f196",
"stats": {
    "name": "09.01.Admin.Portal.AssignJudge",
    "numberOfRequests": {
        "total": 711,
        "ok": 711,
        "ko": 0
    },
    "minResponseTime": {
        "total": 13,
        "ok": 13,
        "ko": 0
    },
    "maxResponseTime": {
        "total": 10810,
        "ok": 10810,
        "ko": 0
    },
    "meanResponseTime": {
        "total": 280,
        "ok": 280,
        "ko": 0
    },
    "standardDeviation": {
        "total": 1002,
        "ok": 1002,
        "ko": 0
    },
    "percentiles1": {
        "total": 18,
        "ok": 18,
        "ko": 0
    },
    "percentiles2": {
        "total": 50,
        "ok": 50,
        "ko": 0
    },
    "percentiles3": {
        "total": 1836,
        "ok": 1836,
        "ko": 0
    },
    "percentiles4": {
        "total": 5082,
        "ok": 5082,
        "ko": 0
    },
    "group1": {
    "name": "t < 800 ms",
    "count": 657,
    "percentage": 92
},
    "group2": {
    "name": "800 ms < t < 1200 ms",
    "count": 7,
    "percentage": 1
},
    "group3": {
    "name": "t > 1200 ms",
    "count": 47,
    "percentage": 7
},
    "group4": {
    "name": "failed",
    "count": 0,
    "percentage": 0
},
    "meanNumberOfRequestsPerSecond": {
        "total": 0.29625,
        "ok": 0.29625,
        "ko": 0
    }
}
    },"req_09-02-admin-por-68219": {
        "type": "REQUEST",
        "name": "09.02.Admin.Portal.AssignJudge",
"path": "09.02.Admin.Portal.AssignJudge",
"pathFormatted": "req_09-02-admin-por-68219",
"stats": {
    "name": "09.02.Admin.Portal.AssignJudge",
    "numberOfRequests": {
        "total": 711,
        "ok": 711,
        "ko": 0
    },
    "minResponseTime": {
        "total": 47,
        "ok": 47,
        "ko": 0
    },
    "maxResponseTime": {
        "total": 17797,
        "ok": 17797,
        "ko": 0
    },
    "meanResponseTime": {
        "total": 393,
        "ok": 393,
        "ko": 0
    },
    "standardDeviation": {
        "total": 683,
        "ok": 683,
        "ko": 0
    },
    "percentiles1": {
        "total": 336,
        "ok": 337,
        "ko": 0
    },
    "percentiles2": {
        "total": 496,
        "ok": 496,
        "ko": 0
    },
    "percentiles3": {
        "total": 656,
        "ok": 656,
        "ko": 0
    },
    "percentiles4": {
        "total": 765,
        "ok": 765,
        "ko": 0
    },
    "group1": {
    "name": "t < 800 ms",
    "count": 706,
    "percentage": 99
},
    "group2": {
    "name": "800 ms < t < 1200 ms",
    "count": 3,
    "percentage": 0
},
    "group3": {
    "name": "t > 1200 ms",
    "count": 2,
    "percentage": 0
},
    "group4": {
    "name": "failed",
    "count": 0,
    "percentage": 0
},
    "meanNumberOfRequestsPerSecond": {
        "total": 0.29625,
        "ok": 0.29625,
        "ko": 0
    }
}
    },"req_10-01-admin-por-2991c": {
        "type": "REQUEST",
        "name": "10.01.Admin.Portal.AddParticipant",
"path": "10.01.Admin.Portal.AddParticipant",
"pathFormatted": "req_10-01-admin-por-2991c",
"stats": {
    "name": "10.01.Admin.Portal.AddParticipant",
    "numberOfRequests": {
        "total": 711,
        "ok": 711,
        "ko": 0
    },
    "minResponseTime": {
        "total": 12,
        "ok": 12,
        "ko": 0
    },
    "maxResponseTime": {
        "total": 6344,
        "ok": 6344,
        "ko": 0
    },
    "meanResponseTime": {
        "total": 181,
        "ok": 181,
        "ko": 0
    },
    "standardDeviation": {
        "total": 635,
        "ok": 635,
        "ko": 0
    },
    "percentiles1": {
        "total": 18,
        "ok": 18,
        "ko": 0
    },
    "percentiles2": {
        "total": 36,
        "ok": 36,
        "ko": 0
    },
    "percentiles3": {
        "total": 1063,
        "ok": 1063,
        "ko": 0
    },
    "percentiles4": {
        "total": 3705,
        "ok": 3705,
        "ko": 0
    },
    "group1": {
    "name": "t < 800 ms",
    "count": 668,
    "percentage": 94
},
    "group2": {
    "name": "800 ms < t < 1200 ms",
    "count": 11,
    "percentage": 2
},
    "group3": {
    "name": "t > 1200 ms",
    "count": 32,
    "percentage": 5
},
    "group4": {
    "name": "failed",
    "count": 0,
    "percentage": 0
},
    "meanNumberOfRequestsPerSecond": {
        "total": 0.29625,
        "ok": 0.29625,
        "ko": 0
    }
}
    },"req_10-02-admin-por-4be35": {
        "type": "REQUEST",
        "name": "10.02.Admin.Portal.AddParticipant",
"path": "10.02.Admin.Portal.AddParticipant",
"pathFormatted": "req_10-02-admin-por-4be35",
"stats": {
    "name": "10.02.Admin.Portal.AddParticipant",
    "numberOfRequests": {
        "total": 706,
        "ok": 706,
        "ko": 0
    },
    "minResponseTime": {
        "total": 58,
        "ok": 58,
        "ko": 0
    },
    "maxResponseTime": {
        "total": 1338,
        "ok": 1338,
        "ko": 0
    },
    "meanResponseTime": {
        "total": 380,
        "ok": 380,
        "ko": 0
    },
    "standardDeviation": {
        "total": 196,
        "ok": 196,
        "ko": 0
    },
    "percentiles1": {
        "total": 350,
        "ok": 350,
        "ko": 0
    },
    "percentiles2": {
        "total": 513,
        "ok": 513,
        "ko": 0
    },
    "percentiles3": {
        "total": 704,
        "ok": 704,
        "ko": 0
    },
    "percentiles4": {
        "total": 900,
        "ok": 900,
        "ko": 0
    },
    "group1": {
    "name": "t < 800 ms",
    "count": 690,
    "percentage": 98
},
    "group2": {
    "name": "800 ms < t < 1200 ms",
    "count": 15,
    "percentage": 2
},
    "group3": {
    "name": "t > 1200 ms",
    "count": 1,
    "percentage": 0
},
    "group4": {
    "name": "failed",
    "count": 0,
    "percentage": 0
},
    "meanNumberOfRequestsPerSecond": {
        "total": 0.2941666666666667,
        "ok": 0.2941666666666667,
        "ko": 0
    }
}
    },"req_10-03-admin-por-59dde": {
        "type": "REQUEST",
        "name": "10.03.Admin.Portal.AddParticipant",
"path": "10.03.Admin.Portal.AddParticipant",
"pathFormatted": "req_10-03-admin-por-59dde",
"stats": {
    "name": "10.03.Admin.Portal.AddParticipant",
    "numberOfRequests": {
        "total": 706,
        "ok": 706,
        "ko": 0
    },
    "minResponseTime": {
        "total": 97,
        "ok": 97,
        "ko": 0
    },
    "maxResponseTime": {
        "total": 18175,
        "ok": 18175,
        "ko": 0
    },
    "meanResponseTime": {
        "total": 1267,
        "ok": 1267,
        "ko": 0
    },
    "standardDeviation": {
        "total": 2718,
        "ok": 2718,
        "ko": 0
    },
    "percentiles1": {
        "total": 200,
        "ok": 200,
        "ko": 0
    },
    "percentiles2": {
        "total": 577,
        "ok": 577,
        "ko": 0
    },
    "percentiles3": {
        "total": 8402,
        "ok": 8402,
        "ko": 0
    },
    "percentiles4": {
        "total": 12389,
        "ok": 12389,
        "ko": 0
    },
    "group1": {
    "name": "t < 800 ms",
    "count": 552,
    "percentage": 78
},
    "group2": {
    "name": "800 ms < t < 1200 ms",
    "count": 18,
    "percentage": 3
},
    "group3": {
    "name": "t > 1200 ms",
    "count": 136,
    "percentage": 19
},
    "group4": {
    "name": "failed",
    "count": 0,
    "percentage": 0
},
    "meanNumberOfRequestsPerSecond": {
        "total": 0.2941666666666667,
        "ok": 0.2941666666666667,
        "ko": 0
    }
}
    },"req_10-04-admin-por-12169": {
        "type": "REQUEST",
        "name": "10.04.Admin.Portal.AddParticipant",
"path": "10.04.Admin.Portal.AddParticipant",
"pathFormatted": "req_10-04-admin-por-12169",
"stats": {
    "name": "10.04.Admin.Portal.AddParticipant",
    "numberOfRequests": {
        "total": 706,
        "ok": 706,
        "ko": 0
    },
    "minResponseTime": {
        "total": 50,
        "ok": 50,
        "ko": 0
    },
    "maxResponseTime": {
        "total": 931,
        "ok": 931,
        "ko": 0
    },
    "meanResponseTime": {
        "total": 389,
        "ok": 389,
        "ko": 0
    },
    "standardDeviation": {
        "total": 185,
        "ok": 185,
        "ko": 0
    },
    "percentiles1": {
        "total": 372,
        "ok": 372,
        "ko": 0
    },
    "percentiles2": {
        "total": 542,
        "ok": 541,
        "ko": 0
    },
    "percentiles3": {
        "total": 690,
        "ok": 690,
        "ko": 0
    },
    "percentiles4": {
        "total": 784,
        "ok": 784,
        "ko": 0
    },
    "group1": {
    "name": "t < 800 ms",
    "count": 702,
    "percentage": 99
},
    "group2": {
    "name": "800 ms < t < 1200 ms",
    "count": 4,
    "percentage": 1
},
    "group3": {
    "name": "t > 1200 ms",
    "count": 0,
    "percentage": 0
},
    "group4": {
    "name": "failed",
    "count": 0,
    "percentage": 0
},
    "meanNumberOfRequestsPerSecond": {
        "total": 0.2941666666666667,
        "ok": 0.2941666666666667,
        "ko": 0
    }
}
    },"req_10-05-admin-por-b99b0": {
        "type": "REQUEST",
        "name": "10.05.Admin.Portal.AddParticipant",
"path": "10.05.Admin.Portal.AddParticipant",
"pathFormatted": "req_10-05-admin-por-b99b0",
"stats": {
    "name": "10.05.Admin.Portal.AddParticipant",
    "numberOfRequests": {
        "total": 705,
        "ok": 705,
        "ko": 0
    },
    "minResponseTime": {
        "total": 12,
        "ok": 12,
        "ko": 0
    },
    "maxResponseTime": {
        "total": 13221,
        "ok": 13221,
        "ko": 0
    },
    "meanResponseTime": {
        "total": 442,
        "ok": 442,
        "ko": 0
    },
    "standardDeviation": {
        "total": 1411,
        "ok": 1411,
        "ko": 0
    },
    "percentiles1": {
        "total": 20,
        "ok": 20,
        "ko": 0
    },
    "percentiles2": {
        "total": 95,
        "ok": 95,
        "ko": 0
    },
    "percentiles3": {
        "total": 3009,
        "ok": 3009,
        "ko": 0
    },
    "percentiles4": {
        "total": 7132,
        "ok": 7132,
        "ko": 0
    },
    "group1": {
    "name": "t < 800 ms",
    "count": 630,
    "percentage": 89
},
    "group2": {
    "name": "800 ms < t < 1200 ms",
    "count": 11,
    "percentage": 2
},
    "group3": {
    "name": "t > 1200 ms",
    "count": 64,
    "percentage": 9
},
    "group4": {
    "name": "failed",
    "count": 0,
    "percentage": 0
},
    "meanNumberOfRequestsPerSecond": {
        "total": 0.29375,
        "ok": 0.29375,
        "ko": 0
    }
}
    },"req_10-06-admin-por-f8c8a": {
        "type": "REQUEST",
        "name": "10.06.Admin.Portal.AddParticipant",
"path": "10.06.Admin.Portal.AddParticipant",
"pathFormatted": "req_10-06-admin-por-f8c8a",
"stats": {
    "name": "10.06.Admin.Portal.AddParticipant",
    "numberOfRequests": {
        "total": 700,
        "ok": 700,
        "ko": 0
    },
    "minResponseTime": {
        "total": 57,
        "ok": 57,
        "ko": 0
    },
    "maxResponseTime": {
        "total": 5584,
        "ok": 5584,
        "ko": 0
    },
    "meanResponseTime": {
        "total": 436,
        "ok": 436,
        "ko": 0
    },
    "standardDeviation": {
        "total": 272,
        "ok": 272,
        "ko": 0
    },
    "percentiles1": {
        "total": 453,
        "ok": 453,
        "ko": 0
    },
    "percentiles2": {
        "total": 568,
        "ok": 568,
        "ko": 0
    },
    "percentiles3": {
        "total": 711,
        "ok": 711,
        "ko": 0
    },
    "percentiles4": {
        "total": 865,
        "ok": 865,
        "ko": 0
    },
    "group1": {
    "name": "t < 800 ms",
    "count": 686,
    "percentage": 98
},
    "group2": {
    "name": "800 ms < t < 1200 ms",
    "count": 13,
    "percentage": 2
},
    "group3": {
    "name": "t > 1200 ms",
    "count": 1,
    "percentage": 0
},
    "group4": {
    "name": "failed",
    "count": 0,
    "percentage": 0
},
    "meanNumberOfRequestsPerSecond": {
        "total": 0.2916666666666667,
        "ok": 0.2916666666666667,
        "ko": 0
    }
}
    },"req_11-01-admin-por-60cf7": {
        "type": "REQUEST",
        "name": "11.01.Admin.Portal.OtherInfo",
"path": "11.01.Admin.Portal.OtherInfo",
"pathFormatted": "req_11-01-admin-por-60cf7",
"stats": {
    "name": "11.01.Admin.Portal.OtherInfo",
    "numberOfRequests": {
        "total": 700,
        "ok": 700,
        "ko": 0
    },
    "minResponseTime": {
        "total": 12,
        "ok": 12,
        "ko": 0
    },
    "maxResponseTime": {
        "total": 14573,
        "ok": 14573,
        "ko": 0
    },
    "meanResponseTime": {
        "total": 440,
        "ok": 440,
        "ko": 0
    },
    "standardDeviation": {
        "total": 1817,
        "ok": 1817,
        "ko": 0
    },
    "percentiles1": {
        "total": 18,
        "ok": 18,
        "ko": 0
    },
    "percentiles2": {
        "total": 53,
        "ok": 53,
        "ko": 0
    },
    "percentiles3": {
        "total": 2101,
        "ok": 2101,
        "ko": 0
    },
    "percentiles4": {
        "total": 14286,
        "ok": 14286,
        "ko": 0
    },
    "group1": {
    "name": "t < 800 ms",
    "count": 637,
    "percentage": 91
},
    "group2": {
    "name": "800 ms < t < 1200 ms",
    "count": 14,
    "percentage": 2
},
    "group3": {
    "name": "t > 1200 ms",
    "count": 49,
    "percentage": 7
},
    "group4": {
    "name": "failed",
    "count": 0,
    "percentage": 0
},
    "meanNumberOfRequestsPerSecond": {
        "total": 0.2916666666666667,
        "ok": 0.2916666666666667,
        "ko": 0
    }
}
    },"req_11-02-admin-por-ddb8a": {
        "type": "REQUEST",
        "name": "11.02.Admin.Portal.OtherInfo",
"path": "11.02.Admin.Portal.OtherInfo",
"pathFormatted": "req_11-02-admin-por-ddb8a",
"stats": {
    "name": "11.02.Admin.Portal.OtherInfo",
    "numberOfRequests": {
        "total": 700,
        "ok": 700,
        "ko": 0
    },
    "minResponseTime": {
        "total": 47,
        "ok": 47,
        "ko": 0
    },
    "maxResponseTime": {
        "total": 1337,
        "ok": 1337,
        "ko": 0
    },
    "meanResponseTime": {
        "total": 383,
        "ok": 383,
        "ko": 0
    },
    "standardDeviation": {
        "total": 191,
        "ok": 191,
        "ko": 0
    },
    "percentiles1": {
        "total": 367,
        "ok": 369,
        "ko": 0
    },
    "percentiles2": {
        "total": 522,
        "ok": 522,
        "ko": 0
    },
    "percentiles3": {
        "total": 693,
        "ok": 693,
        "ko": 0
    },
    "percentiles4": {
        "total": 915,
        "ok": 915,
        "ko": 0
    },
    "group1": {
    "name": "t < 800 ms",
    "count": 688,
    "percentage": 98
},
    "group2": {
    "name": "800 ms < t < 1200 ms",
    "count": 11,
    "percentage": 2
},
    "group3": {
    "name": "t > 1200 ms",
    "count": 1,
    "percentage": 0
},
    "group4": {
    "name": "failed",
    "count": 0,
    "percentage": 0
},
    "meanNumberOfRequestsPerSecond": {
        "total": 0.2916666666666667,
        "ok": 0.2916666666666667,
        "ko": 0
    }
}
    },"req_12-01-admin-por-bc513": {
        "type": "REQUEST",
        "name": "12.01.Admin.Portal.SubmitHearing",
"path": "12.01.Admin.Portal.SubmitHearing",
"pathFormatted": "req_12-01-admin-por-bc513",
"stats": {
    "name": "12.01.Admin.Portal.SubmitHearing",
    "numberOfRequests": {
        "total": 700,
        "ok": 698,
        "ko": 2
    },
    "minResponseTime": {
        "total": 460,
        "ok": 460,
        "ko": 20039
    },
    "maxResponseTime": {
        "total": 20048,
        "ok": 19161,
        "ko": 20048
    },
    "meanResponseTime": {
        "total": 1761,
        "ok": 1709,
        "ko": 20044
    },
    "standardDeviation": {
        "total": 2853,
        "ok": 2684,
        "ko": 5
    },
    "percentiles1": {
        "total": 711,
        "ok": 710,
        "ko": 20044
    },
    "percentiles2": {
        "total": 1243,
        "ok": 1228,
        "ko": 20046
    },
    "percentiles3": {
        "total": 7151,
        "ok": 7003,
        "ko": 20048
    },
    "percentiles4": {
        "total": 14444,
        "ok": 14333,
        "ko": 20048
    },
    "group1": {
    "name": "t < 800 ms",
    "count": 432,
    "percentage": 62
},
    "group2": {
    "name": "800 ms < t < 1200 ms",
    "count": 86,
    "percentage": 12
},
    "group3": {
    "name": "t > 1200 ms",
    "count": 180,
    "percentage": 26
},
    "group4": {
    "name": "failed",
    "count": 2,
    "percentage": 0
},
    "meanNumberOfRequestsPerSecond": {
        "total": 0.2916666666666667,
        "ok": 0.29083333333333333,
        "ko": 8.333333333333334E-4
    }
}
    },"req_12-02-admin-por-82601": {
        "type": "REQUEST",
        "name": "12.02.Admin.Portal.SubmitHearing",
"path": "12.02.Admin.Portal.SubmitHearing",
"pathFormatted": "req_12-02-admin-por-82601",
"stats": {
    "name": "12.02.Admin.Portal.SubmitHearing",
    "numberOfRequests": {
        "total": 695,
        "ok": 695,
        "ko": 0
    },
    "minResponseTime": {
        "total": 12,
        "ok": 12,
        "ko": 0
    },
    "maxResponseTime": {
        "total": 9050,
        "ok": 9050,
        "ko": 0
    },
    "meanResponseTime": {
        "total": 409,
        "ok": 409,
        "ko": 0
    },
    "standardDeviation": {
        "total": 1211,
        "ok": 1211,
        "ko": 0
    },
    "percentiles1": {
        "total": 19,
        "ok": 19,
        "ko": 0
    },
    "percentiles2": {
        "total": 50,
        "ok": 50,
        "ko": 0
    },
    "percentiles3": {
        "total": 2683,
        "ok": 2683,
        "ko": 0
    },
    "percentiles4": {
        "total": 6830,
        "ok": 6830,
        "ko": 0
    },
    "group1": {
    "name": "t < 800 ms",
    "count": 610,
    "percentage": 88
},
    "group2": {
    "name": "800 ms < t < 1200 ms",
    "count": 16,
    "percentage": 2
},
    "group3": {
    "name": "t > 1200 ms",
    "count": 69,
    "percentage": 10
},
    "group4": {
    "name": "failed",
    "count": 0,
    "percentage": 0
},
    "meanNumberOfRequestsPerSecond": {
        "total": 0.28958333333333336,
        "ok": 0.28958333333333336,
        "ko": 0
    }
}
    },"req_12-03-admin-por-f03f8": {
        "type": "REQUEST",
        "name": "12.03.Admin.Portal.SubmitHearing",
"path": "12.03.Admin.Portal.SubmitHearing",
"pathFormatted": "req_12-03-admin-por-f03f8",
"stats": {
    "name": "12.03.Admin.Portal.SubmitHearing",
    "numberOfRequests": {
        "total": 695,
        "ok": 695,
        "ko": 0
    },
    "minResponseTime": {
        "total": 22,
        "ok": 22,
        "ko": 0
    },
    "maxResponseTime": {
        "total": 13918,
        "ok": 13918,
        "ko": 0
    },
    "meanResponseTime": {
        "total": 759,
        "ok": 759,
        "ko": 0
    },
    "standardDeviation": {
        "total": 2062,
        "ok": 2062,
        "ko": 0
    },
    "percentiles1": {
        "total": 47,
        "ok": 47,
        "ko": 0
    },
    "percentiles2": {
        "total": 145,
        "ok": 145,
        "ko": 0
    },
    "percentiles3": {
        "total": 6873,
        "ok": 6873,
        "ko": 0
    },
    "percentiles4": {
        "total": 11149,
        "ok": 11149,
        "ko": 0
    },
    "group1": {
    "name": "t < 800 ms",
    "count": 592,
    "percentage": 85
},
    "group2": {
    "name": "800 ms < t < 1200 ms",
    "count": 12,
    "percentage": 2
},
    "group3": {
    "name": "t > 1200 ms",
    "count": 91,
    "percentage": 13
},
    "group4": {
    "name": "failed",
    "count": 0,
    "percentage": 0
},
    "meanNumberOfRequestsPerSecond": {
        "total": 0.28958333333333336,
        "ok": 0.28958333333333336,
        "ko": 0
    }
}
    },"req_12-04-admin-por-e6f4c": {
        "type": "REQUEST",
        "name": "12.04.Admin.Portal.SubmitHearing",
"path": "12.04.Admin.Portal.SubmitHearing",
"pathFormatted": "req_12-04-admin-por-e6f4c",
"stats": {
    "name": "12.04.Admin.Portal.SubmitHearing",
    "numberOfRequests": {
        "total": 695,
        "ok": 695,
        "ko": 0
    },
    "minResponseTime": {
        "total": 47,
        "ok": 47,
        "ko": 0
    },
    "maxResponseTime": {
        "total": 3031,
        "ok": 3031,
        "ko": 0
    },
    "meanResponseTime": {
        "total": 406,
        "ok": 406,
        "ko": 0
    },
    "standardDeviation": {
        "total": 218,
        "ok": 218,
        "ko": 0
    },
    "percentiles1": {
        "total": 399,
        "ok": 399,
        "ko": 0
    },
    "percentiles2": {
        "total": 559,
        "ok": 559,
        "ko": 0
    },
    "percentiles3": {
        "total": 686,
        "ok": 686,
        "ko": 0
    },
    "percentiles4": {
        "total": 831,
        "ok": 831,
        "ko": 0
    },
    "group1": {
    "name": "t < 800 ms",
    "count": 684,
    "percentage": 98
},
    "group2": {
    "name": "800 ms < t < 1200 ms",
    "count": 9,
    "percentage": 1
},
    "group3": {
    "name": "t > 1200 ms",
    "count": 2,
    "percentage": 0
},
    "group4": {
    "name": "failed",
    "count": 0,
    "percentage": 0
},
    "meanNumberOfRequestsPerSecond": {
        "total": 0.28958333333333336,
        "ok": 0.28958333333333336,
        "ko": 0
    }
}
    },"req_13-01-admin-por-c563a": {
        "type": "REQUEST",
        "name": "13.01.Admin.Portal.Booking.List",
"path": "13.01.Admin.Portal.Booking.List",
"pathFormatted": "req_13-01-admin-por-c563a",
"stats": {
    "name": "13.01.Admin.Portal.Booking.List",
    "numberOfRequests": {
        "total": 695,
        "ok": 695,
        "ko": 0
    },
    "minResponseTime": {
        "total": 12,
        "ok": 12,
        "ko": 0
    },
    "maxResponseTime": {
        "total": 2602,
        "ok": 2602,
        "ko": 0
    },
    "meanResponseTime": {
        "total": 76,
        "ok": 76,
        "ko": 0
    },
    "standardDeviation": {
        "total": 238,
        "ok": 238,
        "ko": 0
    },
    "percentiles1": {
        "total": 19,
        "ok": 19,
        "ko": 0
    },
    "percentiles2": {
        "total": 38,
        "ok": 38,
        "ko": 0
    },
    "percentiles3": {
        "total": 253,
        "ok": 253,
        "ko": 0
    },
    "percentiles4": {
        "total": 1022,
        "ok": 1022,
        "ko": 0
    },
    "group1": {
    "name": "t < 800 ms",
    "count": 684,
    "percentage": 98
},
    "group2": {
    "name": "800 ms < t < 1200 ms",
    "count": 5,
    "percentage": 1
},
    "group3": {
    "name": "t > 1200 ms",
    "count": 6,
    "percentage": 1
},
    "group4": {
    "name": "failed",
    "count": 0,
    "percentage": 0
},
    "meanNumberOfRequestsPerSecond": {
        "total": 0.28958333333333336,
        "ok": 0.28958333333333336,
        "ko": 0
    }
}
    },"req_13-02-admin-por-871d6": {
        "type": "REQUEST",
        "name": "13.02.Admin.Portal.Booking.List",
"path": "13.02.Admin.Portal.Booking.List",
"pathFormatted": "req_13-02-admin-por-871d6",
"stats": {
    "name": "13.02.Admin.Portal.Booking.List",
    "numberOfRequests": {
        "total": 695,
        "ok": 695,
        "ko": 0
    },
    "minResponseTime": {
        "total": 41,
        "ok": 41,
        "ko": 0
    },
    "maxResponseTime": {
        "total": 16990,
        "ok": 16990,
        "ko": 0
    },
    "meanResponseTime": {
        "total": 775,
        "ok": 775,
        "ko": 0
    },
    "standardDeviation": {
        "total": 1699,
        "ok": 1699,
        "ko": 0
    },
    "percentiles1": {
        "total": 195,
        "ok": 196,
        "ko": 0
    },
    "percentiles2": {
        "total": 531,
        "ok": 531,
        "ko": 0
    },
    "percentiles3": {
        "total": 3043,
        "ok": 3043,
        "ko": 0
    },
    "percentiles4": {
        "total": 7598,
        "ok": 7598,
        "ko": 0
    },
    "group1": {
    "name": "t < 800 ms",
    "count": 555,
    "percentage": 80
},
    "group2": {
    "name": "800 ms < t < 1200 ms",
    "count": 25,
    "percentage": 4
},
    "group3": {
    "name": "t > 1200 ms",
    "count": 115,
    "percentage": 17
},
    "group4": {
    "name": "failed",
    "count": 0,
    "percentage": 0
},
    "meanNumberOfRequestsPerSecond": {
        "total": 0.28958333333333336,
        "ok": 0.28958333333333336,
        "ko": 0
    }
}
    },"req_13-03-admin-por-82247": {
        "type": "REQUEST",
        "name": "13.03.Admin.Portal.Booking.List",
"path": "13.03.Admin.Portal.Booking.List",
"pathFormatted": "req_13-03-admin-por-82247",
"stats": {
    "name": "13.03.Admin.Portal.Booking.List",
    "numberOfRequests": {
        "total": 695,
        "ok": 695,
        "ko": 0
    },
    "minResponseTime": {
        "total": 51,
        "ok": 51,
        "ko": 0
    },
    "maxResponseTime": {
        "total": 1194,
        "ok": 1194,
        "ko": 0
    },
    "meanResponseTime": {
        "total": 414,
        "ok": 414,
        "ko": 0
    },
    "standardDeviation": {
        "total": 182,
        "ok": 182,
        "ko": 0
    },
    "percentiles1": {
        "total": 422,
        "ok": 422,
        "ko": 0
    },
    "percentiles2": {
        "total": 551,
        "ok": 551,
        "ko": 0
    },
    "percentiles3": {
        "total": 678,
        "ok": 678,
        "ko": 0
    },
    "percentiles4": {
        "total": 852,
        "ok": 852,
        "ko": 0
    },
    "group1": {
    "name": "t < 800 ms",
    "count": 683,
    "percentage": 98
},
    "group2": {
    "name": "800 ms < t < 1200 ms",
    "count": 12,
    "percentage": 2
},
    "group3": {
    "name": "t > 1200 ms",
    "count": 0,
    "percentage": 0
},
    "group4": {
    "name": "failed",
    "count": 0,
    "percentage": 0
},
    "meanNumberOfRequestsPerSecond": {
        "total": 0.28958333333333336,
        "ok": 0.28958333333333336,
        "ko": 0
    }
}
    },"req_14-01-admin-por-4639e": {
        "type": "REQUEST",
        "name": "14.01.Admin.Portal.Booking.Drilldown",
"path": "14.01.Admin.Portal.Booking.Drilldown",
"pathFormatted": "req_14-01-admin-por-4639e",
"stats": {
    "name": "14.01.Admin.Portal.Booking.Drilldown",
    "numberOfRequests": {
        "total": 695,
        "ok": 695,
        "ko": 0
    },
    "minResponseTime": {
        "total": 13,
        "ok": 13,
        "ko": 0
    },
    "maxResponseTime": {
        "total": 12334,
        "ok": 12334,
        "ko": 0
    },
    "meanResponseTime": {
        "total": 106,
        "ok": 106,
        "ko": 0
    },
    "standardDeviation": {
        "total": 552,
        "ok": 552,
        "ko": 0
    },
    "percentiles1": {
        "total": 18,
        "ok": 18,
        "ko": 0
    },
    "percentiles2": {
        "total": 36,
        "ok": 36,
        "ko": 0
    },
    "percentiles3": {
        "total": 350,
        "ok": 350,
        "ko": 0
    },
    "percentiles4": {
        "total": 1599,
        "ok": 1599,
        "ko": 0
    },
    "group1": {
    "name": "t < 800 ms",
    "count": 679,
    "percentage": 98
},
    "group2": {
    "name": "800 ms < t < 1200 ms",
    "count": 6,
    "percentage": 1
},
    "group3": {
    "name": "t > 1200 ms",
    "count": 10,
    "percentage": 1
},
    "group4": {
    "name": "failed",
    "count": 0,
    "percentage": 0
},
    "meanNumberOfRequestsPerSecond": {
        "total": 0.28958333333333336,
        "ok": 0.28958333333333336,
        "ko": 0
    }
}
    },"req_14-02-admin-por-7fd90": {
        "type": "REQUEST",
        "name": "14.02.Admin.Portal.Booking.Drilldown",
"path": "14.02.Admin.Portal.Booking.Drilldown",
"pathFormatted": "req_14-02-admin-por-7fd90",
"stats": {
    "name": "14.02.Admin.Portal.Booking.Drilldown",
    "numberOfRequests": {
        "total": 695,
        "ok": 695,
        "ko": 0
    },
    "minResponseTime": {
        "total": 22,
        "ok": 22,
        "ko": 0
    },
    "maxResponseTime": {
        "total": 15658,
        "ok": 15658,
        "ko": 0
    },
    "meanResponseTime": {
        "total": 338,
        "ok": 338,
        "ko": 0
    },
    "standardDeviation": {
        "total": 1398,
        "ok": 1398,
        "ko": 0
    },
    "percentiles1": {
        "total": 47,
        "ok": 47,
        "ko": 0
    },
    "percentiles2": {
        "total": 93,
        "ok": 93,
        "ko": 0
    },
    "percentiles3": {
        "total": 1034,
        "ok": 1034,
        "ko": 0
    },
    "percentiles4": {
        "total": 7069,
        "ok": 7069,
        "ko": 0
    },
    "group1": {
    "name": "t < 800 ms",
    "count": 652,
    "percentage": 94
},
    "group2": {
    "name": "800 ms < t < 1200 ms",
    "count": 11,
    "percentage": 2
},
    "group3": {
    "name": "t > 1200 ms",
    "count": 32,
    "percentage": 5
},
    "group4": {
    "name": "failed",
    "count": 0,
    "percentage": 0
},
    "meanNumberOfRequestsPerSecond": {
        "total": 0.28958333333333336,
        "ok": 0.28958333333333336,
        "ko": 0
    }
}
    },"req_14-03-admin-por-6d10b": {
        "type": "REQUEST",
        "name": "14.03.Admin.Portal.Booking.Drilldown",
"path": "14.03.Admin.Portal.Booking.Drilldown",
"pathFormatted": "req_14-03-admin-por-6d10b",
"stats": {
    "name": "14.03.Admin.Portal.Booking.Drilldown",
    "numberOfRequests": {
        "total": 695,
        "ok": 695,
        "ko": 0
    },
    "minResponseTime": {
        "total": 12,
        "ok": 12,
        "ko": 0
    },
    "maxResponseTime": {
        "total": 3964,
        "ok": 3964,
        "ko": 0
    },
    "meanResponseTime": {
        "total": 39,
        "ok": 39,
        "ko": 0
    },
    "standardDeviation": {
        "total": 194,
        "ok": 194,
        "ko": 0
    },
    "percentiles1": {
        "total": 17,
        "ok": 17,
        "ko": 0
    },
    "percentiles2": {
        "total": 22,
        "ok": 22,
        "ko": 0
    },
    "percentiles3": {
        "total": 67,
        "ok": 67,
        "ko": 0
    },
    "percentiles4": {
        "total": 389,
        "ok": 389,
        "ko": 0
    },
    "group1": {
    "name": "t < 800 ms",
    "count": 691,
    "percentage": 99
},
    "group2": {
    "name": "800 ms < t < 1200 ms",
    "count": 1,
    "percentage": 0
},
    "group3": {
    "name": "t > 1200 ms",
    "count": 3,
    "percentage": 0
},
    "group4": {
    "name": "failed",
    "count": 0,
    "percentage": 0
},
    "meanNumberOfRequestsPerSecond": {
        "total": 0.28958333333333336,
        "ok": 0.28958333333333336,
        "ko": 0
    }
}
    },"req_14-04-admin-por-170f0": {
        "type": "REQUEST",
        "name": "14.04.Admin.Portal.Booking.Drilldown",
"path": "14.04.Admin.Portal.Booking.Drilldown",
"pathFormatted": "req_14-04-admin-por-170f0",
"stats": {
    "name": "14.04.Admin.Portal.Booking.Drilldown",
    "numberOfRequests": {
        "total": 695,
        "ok": 695,
        "ko": 0
    },
    "minResponseTime": {
        "total": 52,
        "ok": 52,
        "ko": 0
    },
    "maxResponseTime": {
        "total": 17874,
        "ok": 17874,
        "ko": 0
    },
    "meanResponseTime": {
        "total": 446,
        "ok": 446,
        "ko": 0
    },
    "standardDeviation": {
        "total": 687,
        "ok": 687,
        "ko": 0
    },
    "percentiles1": {
        "total": 450,
        "ok": 450,
        "ko": 0
    },
    "percentiles2": {
        "total": 551,
        "ok": 551,
        "ko": 0
    },
    "percentiles3": {
        "total": 693,
        "ok": 693,
        "ko": 0
    },
    "percentiles4": {
        "total": 818,
        "ok": 818,
        "ko": 0
    },
    "group1": {
    "name": "t < 800 ms",
    "count": 684,
    "percentage": 98
},
    "group2": {
    "name": "800 ms < t < 1200 ms",
    "count": 10,
    "percentage": 1
},
    "group3": {
    "name": "t > 1200 ms",
    "count": 1,
    "percentage": 0
},
    "group4": {
    "name": "failed",
    "count": 0,
    "percentage": 0
},
    "meanNumberOfRequestsPerSecond": {
        "total": 0.28958333333333336,
        "ok": 0.28958333333333336,
        "ko": 0
    }
}
    },"req_15-01-admin-por-845b6": {
        "type": "REQUEST",
        "name": "15.01.Admin.Portal.SendToVideoApp",
"path": "15.01.Admin.Portal.SendToVideoApp",
"pathFormatted": "req_15-01-admin-por-845b6",
"stats": {
    "name": "15.01.Admin.Portal.SendToVideoApp",
    "numberOfRequests": {
        "total": 695,
        "ok": 693,
        "ko": 2
    },
    "minResponseTime": {
        "total": 72,
        "ok": 72,
        "ko": 1762
    },
    "maxResponseTime": {
        "total": 14200,
        "ok": 14200,
        "ko": 3412
    },
    "meanResponseTime": {
        "total": 450,
        "ok": 443,
        "ko": 2587
    },
    "standardDeviation": {
        "total": 1494,
        "ok": 1491,
        "ko": 825
    },
    "percentiles1": {
        "total": 140,
        "ok": 140,
        "ko": 2587
    },
    "percentiles2": {
        "total": 225,
        "ok": 224,
        "ko": 3000
    },
    "percentiles3": {
        "total": 1356,
        "ok": 1322,
        "ko": 3329
    },
    "percentiles4": {
        "total": 10535,
        "ok": 10546,
        "ko": 3396
    },
    "group1": {
    "name": "t < 800 ms",
    "count": 644,
    "percentage": 93
},
    "group2": {
    "name": "800 ms < t < 1200 ms",
    "count": 10,
    "percentage": 1
},
    "group3": {
    "name": "t > 1200 ms",
    "count": 39,
    "percentage": 6
},
    "group4": {
    "name": "failed",
    "count": 2,
    "percentage": 0
},
    "meanNumberOfRequestsPerSecond": {
        "total": 0.28958333333333336,
        "ok": 0.28875,
        "ko": 8.333333333333334E-4
    }
}
    },"req_15-02-admin-por-b1b19": {
        "type": "REQUEST",
        "name": "15.02.Admin.Portal.SendToVideoApp",
"path": "15.02.Admin.Portal.SendToVideoApp",
"pathFormatted": "req_15-02-admin-por-b1b19",
"stats": {
    "name": "15.02.Admin.Portal.SendToVideoApp",
    "numberOfRequests": {
        "total": 682,
        "ok": 682,
        "ko": 0
    },
    "minResponseTime": {
        "total": 23,
        "ok": 23,
        "ko": 0
    },
    "maxResponseTime": {
        "total": 15724,
        "ok": 15724,
        "ko": 0
    },
    "meanResponseTime": {
        "total": 1464,
        "ok": 1464,
        "ko": 0
    },
    "standardDeviation": {
        "total": 3017,
        "ok": 3017,
        "ko": 0
    },
    "percentiles1": {
        "total": 51,
        "ok": 52,
        "ko": 0
    },
    "percentiles2": {
        "total": 802,
        "ok": 802,
        "ko": 0
    },
    "percentiles3": {
        "total": 8221,
        "ok": 8221,
        "ko": 0
    },
    "percentiles4": {
        "total": 13200,
        "ok": 13200,
        "ko": 0
    },
    "group1": {
    "name": "t < 800 ms",
    "count": 511,
    "percentage": 75
},
    "group2": {
    "name": "800 ms < t < 1200 ms",
    "count": 14,
    "percentage": 2
},
    "group3": {
    "name": "t > 1200 ms",
    "count": 157,
    "percentage": 23
},
    "group4": {
    "name": "failed",
    "count": 0,
    "percentage": 0
},
    "meanNumberOfRequestsPerSecond": {
        "total": 0.2841666666666667,
        "ok": 0.2841666666666667,
        "ko": 0
    }
}
    },"req_15-03-admin-por-ff12f": {
        "type": "REQUEST",
        "name": "15.03.Admin.Portal.SendToVideoApp",
"path": "15.03.Admin.Portal.SendToVideoApp",
"pathFormatted": "req_15-03-admin-por-ff12f",
"stats": {
    "name": "15.03.Admin.Portal.SendToVideoApp",
    "numberOfRequests": {
        "total": 682,
        "ok": 682,
        "ko": 0
    },
    "minResponseTime": {
        "total": 46,
        "ok": 46,
        "ko": 0
    },
    "maxResponseTime": {
        "total": 1520,
        "ok": 1520,
        "ko": 0
    },
    "meanResponseTime": {
        "total": 416,
        "ok": 416,
        "ko": 0
    },
    "standardDeviation": {
        "total": 198,
        "ok": 198,
        "ko": 0
    },
    "percentiles1": {
        "total": 423,
        "ok": 423,
        "ko": 0
    },
    "percentiles2": {
        "total": 562,
        "ok": 562,
        "ko": 0
    },
    "percentiles3": {
        "total": 704,
        "ok": 704,
        "ko": 0
    },
    "percentiles4": {
        "total": 876,
        "ok": 876,
        "ko": 0
    },
    "group1": {
    "name": "t < 800 ms",
    "count": 670,
    "percentage": 98
},
    "group2": {
    "name": "800 ms < t < 1200 ms",
    "count": 10,
    "percentage": 1
},
    "group3": {
    "name": "t > 1200 ms",
    "count": 2,
    "percentage": 0
},
    "group4": {
    "name": "failed",
    "count": 0,
    "percentage": 0
},
    "meanNumberOfRequestsPerSecond": {
        "total": 0.2841666666666667,
        "ok": 0.2841666666666667,
        "ko": 0
    }
}
    },"req_16-00-admin-por-3f7b6": {
        "type": "REQUEST",
        "name": "16.00.Admin.Portal.Logout",
"path": "16.00.Admin.Portal.Logout",
"pathFormatted": "req_16-00-admin-por-3f7b6",
"stats": {
    "name": "16.00.Admin.Portal.Logout",
    "numberOfRequests": {
        "total": 682,
        "ok": 682,
        "ko": 0
    },
    "minResponseTime": {
        "total": 166,
        "ok": 166,
        "ko": 0
    },
    "maxResponseTime": {
        "total": 651,
        "ok": 651,
        "ko": 0
    },
    "meanResponseTime": {
        "total": 255,
        "ok": 255,
        "ko": 0
    },
    "standardDeviation": {
        "total": 65,
        "ok": 65,
        "ko": 0
    },
    "percentiles1": {
        "total": 233,
        "ok": 233,
        "ko": 0
    },
    "percentiles2": {
        "total": 271,
        "ok": 271,
        "ko": 0
    },
    "percentiles3": {
        "total": 386,
        "ok": 386,
        "ko": 0
    },
    "percentiles4": {
        "total": 519,
        "ok": 519,
        "ko": 0
    },
    "group1": {
    "name": "t < 800 ms",
    "count": 682,
    "percentage": 100
},
    "group2": {
    "name": "800 ms < t < 1200 ms",
    "count": 0,
    "percentage": 0
},
    "group3": {
    "name": "t > 1200 ms",
    "count": 0,
    "percentage": 0
},
    "group4": {
    "name": "failed",
    "count": 0,
    "percentage": 0
},
    "meanNumberOfRequestsPerSecond": {
        "total": 0.2841666666666667,
        "ok": 0.2841666666666667,
        "ko": 0
    }
}
    }
}

}